json_tools_rs-0.7.0.dist-info/METADATA
json_tools_rs-0.7.0.dist-info/WHEEL
json_tools_rs/__init__.py
json_tools_rs/json_tools_rs.cpython-313-aarch64-linux-gnu.so
json_tools_rs/py.typed
json_tools_rs-0.7.0.dist-info/RECORD
