Metadata-Version: 2.4
Name: json-tools-rs
Version: 0.7.0
Classifier: Development Status :: 4 - Beta
Classifier: Intended Audience :: Developers
Classifier: License :: OSI Approved :: MIT License
Classifier: License :: OSI Approved :: Apache Software License
Classifier: Operating System :: OS Independent
Classifier: Programming Language :: Python :: 3
Classifier: Programming Language :: Python :: 3.8
Classifier: Programming Language :: Python :: 3.9
Classifier: Programming Language :: Python :: 3.10
Classifier: Programming Language :: Python :: 3.11
Classifier: Programming Language :: Python :: 3.12
Classifier: Programming Language :: Python :: 3.13
Classifier: Programming Language :: Rust
Classifier: Topic :: Software Development :: Libraries :: Python Modules
Classifier: Topic :: Text Processing :: General
Classifier: Topic :: Utilities
Summary: High-performance JSON manipulation library with SIMD-accelerated parsing and automatic type conversion
Keywords: json,flatten,manipulation,parsing,rust,simd,performance
Author: JSON Tools RS Contributors
License: MIT OR Apache-2.0
Requires-Python: >=3.8
Project-URL: Homepage, https://github.com/amaye15/JSON-Tools-rs
Project-URL: Repository, https://github.com/amaye15/JSON-Tools-rs
Project-URL: Documentation, https://github.com/amaye15/JSON-Tools-rs#readme
Project-URL: Bug Tracker, https://github.com/amaye15/JSON-Tools-rs/issues
